sunsynk/__init__.py
sunsynk/definitions/__init__.py
sunsynk/definitions/single_phase.py
sunsynk/definitions/single_phase_16kw.py
sunsynk/definitions/three_phase_common.py
sunsynk/definitions/three_phase_hv.py
sunsynk/definitions/three_phase_lv.py
sunsynk/helpers.py
sunsynk/py.typed
sunsynk/pysunsynk.py
sunsynk/rwsensors.py
sunsynk/sensors.py
sunsynk/solarmansunsynk.py
sunsynk/state.py
sunsynk/sunsynk.py
sunsynk/usunsynk.py
sunsynk/utils.py
ha_addon_sunsynk_multi/__init__.py
ha_addon_sunsynk_multi/__main__.py
ha_addon_sunsynk_multi/a_inverter.py
ha_addon_sunsynk_multi/a_sensor.py
ha_addon_sunsynk_multi/driver.py
ha_addon_sunsynk_multi/errors.py
ha_addon_sunsynk_multi/helpers.py
ha_addon_sunsynk_multi/options.py
ha_addon_sunsynk_multi/sensor_callback.py
ha_addon_sunsynk_multi/sensor_options.py
ha_addon_sunsynk_multi/timer_callback.py
ha_addon_sunsynk_multi/timer_schedule.py
sunsynk-0.9.0.dist-info/WHEEL
sunsynk-0.9.0.dist-info/METADATA
sunsynk-0.9.0.dist-info/RECORD
