Metadata-Version: 2.3
Name: sunsynk
Version: 0.9.0
Summary: Library to interface Deye/Sunsynk Hybrid Inverters
Keywords: asyncio,deye,inverter,modbus,sunsynk
Author: Johann Kellerman
Author-email: Johann Kellerman <kellerza@gmail.com>
License: Apache-2.0
Classifier: Development Status :: 4 - Beta
Classifier: Intended Audience :: Developers
Classifier: Natural Language :: English
Classifier: Programming Language :: Python :: 3 :: Only
Classifier: Programming Language :: Python :: 3.12
Classifier: Programming Language :: Python :: 3.13
Classifier: Programming Language :: Python :: 3.14
Requires-Dist: attrs>=25,<26
Requires-Dist: cattrs>=25,<26
Requires-Dist: mqtt-entity[options]>=1,<2
Requires-Dist: prettytable==3.16
Requires-Dist: pymodbus[serial]==3.11.3
Requires-Dist: pysolarmanv5==3.0.6 ; extra == 'solarman'
Requires-Dist: async-modbus==0.2.2 ; extra == 'umodbus'
Requires-Dist: connio==0.2 ; extra == 'umodbus'
Requires-Dist: umodbus==1.0.4 ; extra == 'umodbus'
Requires-Python: >=3.12
Project-URL: Homepage, https://kellerza.github.io/sunsynk/
Provides-Extra: solarman
Provides-Extra: umodbus
